[{
    "id": 1,
    "name": "Stim",
    "description": "Nullam porttitor lacus at turpis. Donec posuere metus vitae ipsum. Aliquam non mauris.",
    "startDate": "11/21/2022",
    "endDate": "2/10/2023"
  }, {
    "id": 2,
    "name": "Opela",
    "description": "Duis bibendum. Morbi non quam nec dui luctus rutrum. Nulla tellus.",
    "startDate": "11/20/2022",
    "endDate": "2/19/2023"
  }, {
    "id": 3,
    "name": "Pannier",
    "description": "Maecenas ut massa quis augue luctus tincidunt. Nulla mollis molestie lorem. Quisque ut erat.",
    "startDate": "11/8/2022",
    "endDate": "2/20/2023"
  }, {
    "id": 4,
    "name": "Tampflex",
    "description": "Nulla ut erat id mauris vulputate elementum. Nullam varius. Nulla facilisi.",
    "startDate": "10/24/2022",
    "endDate": "1/26/2023"
  }, {
    "id": 5,
    "name": "Domainer",
    "description": "Maecenas tristique, est et tempus semper, est quam pharetra magna, ac consequat metus sapien ut nunc. Vestibulum ante ipsum primis in faucibus orci luctus et ultrices posuere cubilia Curae; Mauris viverra diam vitae quam. Suspendisse potenti.",
    "startDate": "10/21/2022",
    "endDate": "12/30/2022"
  }, {
    "id": 6,
    "name": "Vagram",
    "description": "In congue. Etiam justo. Etiam pretium iaculis justo.",
    "startDate": "11/14/2022",
    "endDate": "2/5/2023"
  }, {
    "id": 7,
    "name": "Opela",
    "description": "In sagittis dui vel nisl. Duis ac nibh. Fusce lacus purus, aliquet at, feugiat non, pretium quis, lectus.",
    "startDate": "11/26/2022",
    "endDate": "1/14/2023"
  }, {
    "id": 8,
    "name": "Toughjoyfax",
    "description": "Phasellus sit amet erat. Nulla tempus. Vivamus in felis eu sapien cursus vestibulum.",
    "startDate": "10/14/2022",
    "endDate": "1/4/2023"
  }, {
    "id": 9,
    "name": "Holdlamis",
    "description": "Quisque id justo sit amet sapien dignissim vestibulum. Vestibulum ante ipsum primis in faucibus orci luctus et ultrices posuere cubilia Curae; Nulla dapibus dolor vel est. Donec odio justo, sollicitudin ut, suscipit a, feugiat et, eros.",
    "startDate": "10/28/2022",
    "endDate": "1/5/2023"
  }, {
    "id": 10,
    "name": "Opela",
    "description": "Duis bibendum. Morbi non quam nec dui luctus rutrum. Nulla tellus.",
    "startDate": "11/21/2022",
    "endDate": "1/31/2023"
  }]
